<?xml version="1.0"?>
<opencv_storage>
<stage0>
  <maxWeakCount>4</maxWeakCount>
  <stageThreshold>-1.3268288373947144e+00</stageThreshold>
  <weakClassifiers>
    <_>
      <internalNodes>
        0 -1 115689 -3.2604206353425980e-02</internalNodes>
      <leafValues>
        7.5000000000000000e-01 -9.0769231319427490e-01</leafValues></_>
    <_>
      <internalNodes>
        0 -1 146276 -9.4451457262039185e-03</internalNodes>
      <leafValues>
        5.6921559572219849e-01 -7.5672233104705811e-01</leafValues></_>
    <_>
      <internalNodes>
        0 -1 119310 6.0342201031744480e-03</internalNodes>
      <leafValues>
        -5.1122099161148071e-01 8.4291511774063110e-01</leafValues></_>
    <_>
      <internalNodes>
        0 -1 67272 -1.0728934779763222e-02</internalNodes>
      <leafValues>
        8.4880673885345459e-01 -4.7559869289398193e-01</leafValues></_></weakClassifiers></stage0>
</opencv_storage>
